README.md
setup.py
ChenChaoFan/HTMLReport.py
ChenChaoFan/__init__.py
ChenChaoFan/templates/__init__.py
chenchaofan.egg-info/PKG-INFO
chenchaofan.egg-info/SOURCES.txt
chenchaofan.egg-info/dependency_links.txt
chenchaofan.egg-info/top_level.txt