Metadata-Version: 1.0
Name: chenchaofan
Version: 1.1.1
Summary: time and path tool
Home-page: https://github.com/a654721574/ccf123.git
Author: a654721574
Author-email: 654721574@qq.com
License: MIT Licence
Keywords: pip,pathtool,timetool,chenchaofan,mage
Platform: any
